vegoia/__init__.py
vegoia/grid.py
vegoia/isoline.py
vegoia/lip.py
vegoia/square.py
vegoia/types.py
vegoia-0.1.0.dist-info/WHEEL
vegoia-0.1.0.dist-info/METADATA
vegoia-0.1.0.dist-info/RECORD
