Metadata-Version: 2.1
Name: vegoia
Version: 0.1.0
Summary: Python adaptive plotting library
License: MIT
Author: Denis Rosset
Author-email: physics@denisrosset.com
Requires-Python: >=3.7,<3.11
Classifier: License :: OSI Approved :: MIT License
Classifier: Programming Language :: Python :: 3
Classifier: Programming Language :: Python :: 3.10
Classifier: Programming Language :: Python :: 3.7
Classifier: Programming Language :: Python :: 3.8
Classifier: Programming Language :: Python :: 3.9
Provides-Extra: beartype
Provides-Extra: docs
Requires-Dist: beartype (>=0.10.4,<0.11.0); extra == "beartype"
Requires-Dist: matplotlib (>=3.0,<4.0)
Requires-Dist: myst-nb (>=0.13.2,<0.14.0); extra == "docs"
Requires-Dist: numpy (>=1.21,<2.0)
Requires-Dist: scipy (>=1.7.0,<2.0.0)
Requires-Dist: sphinx (==4.3.2); extra == "docs"
Requires-Dist: sphinx-autodoc-typehints (>=1.17.0,<2.0.0); extra == "docs"
Requires-Dist: sphinx-book-theme (>=0.2.0,<0.3.0); extra == "docs"
Requires-Dist: typing-extensions (>=4.1.1,<5.0.0)
